{
  "version": 1,
  "license": "CC-BY-SA-3.0",
  "copyright": "https://github.com/yogstation13/Yogstation/blob/7eb1e4c0a1b012a8aacf09b5e6c3923630521cc4/icons/mob/ipc_accessories.dmi",
  "size": {
    "x": 32,
    "y": 32
  },
  "states": [
	{
      "name": "ipc_head",
      "directions": 4
    },
	{
      "name": "diodes-unshaded",
      "directions": 4
    },
	{
      "name": "segments",
      "directions": 4
    },
	{
      "name": "human_torso_m",
      "directions": 4
    },
	{
      "name": "human_torso_f",
      "directions": 4
    },
	{
      "name": "human_head_m",
      "directions": 4
    },
	{
      "name": "human_head_f",
      "directions": 4
    },
	{
      "name": "human_jaw_m",
      "directions": 4
    },
	{
      "name": "human_jaw_f",
      "directions": 4
    },
	{
      "name": "human_eyes-unshaded",
      "directions": 4
    },
	{
      "name": "human_l_arm",
      "directions": 4
    },
	{
      "name": "human_r_arm",
      "directions": 4
    },
	{
      "name": "human_l_leg",
      "directions": 4
    },
	{
      "name": "human_r_leg",
      "directions": 4
    },
	{
      "name": "human_l_hand",
      "directions": 4
    },
	{
      "name": "human_r_hand",
      "directions": 4
    },
	{
      "name": "human_l_foot",
      "directions": 4
    },
	{
      "name": "human_r_foot",
      "directions": 4
    },
	{
      "name": "n1_chest",
      "directions": 4
    },
	{
      "name": "n1_head",
      "directions": 4
    },
	{
      "name": "n1_monoeye",
      "directions": 4
    },
	{
      "name": "n1_l_arm",
      "directions": 4
    },
	{
      "name": "n1_r_arm",
      "directions": 4
    },
	{
      "name": "n1_l_leg",
      "directions": 4
    },
	{
      "name": "n1_r_leg",
      "directions": 4
    },
	{
      "name": "n1_l_hand",
      "directions": 4
    },
	{
      "name": "n1_r_hand",
      "directions": 4
    },
	{
      "name": "n1_l_foot",
      "directions": 4
    },
	{
      "name": "n1_r_foot",
      "directions": 4
    },
	{
      "name": "des_head",
      "directions": 4
    },
	{
      "name": "des_head_monitor",
      "directions": 4
    },
	{
      "name": "des_chest",
      "directions": 4
    },
	{
      "name": "des_l_arm",
      "directions": 4
    },
	{
      "name": "des_r_arm",
      "directions": 4
    },
	{
      "name": "des_l_leg",
      "directions": 4
    },
	{
      "name": "des_r_leg",
      "directions": 4
    },
	{
      "name": "des_l_hand",
      "directions": 4
    },
	{
      "name": "des_r_hand",
      "directions": 4
    },
	{
      "name": "des_l_foot",
      "directions": 4
    },
	{
      "name": "des_r_foot",
      "directions": 4
    },
	{
      "name": "renuin_head_monitor",
      "directions": 4
    },
	{
      "name": "renuin_chest",
      "directions": 4
    },
	{
      "name": "renuin_l_arm",
      "directions": 4
    },
	{
      "name": "renuin_r_arm",
      "directions": 4
    },
	{
      "name": "renuin_l_leg",
      "directions": 4
    },
	{
      "name": "renuin_r_leg",
      "directions": 4
    },
	{
      "name": "renuin_l_hand",
      "directions": 4
    },
	{
      "name": "renuin_r_hand",
      "directions": 4
    },
	{
      "name": "renuin_l_foot",
      "directions": 4
    },
	{
      "name": "renuin_r_foot",
      "directions": 4
    },
	{
      "name": "bishop_head",
      "directions": 4
    },
	{
      "name": "bishop_head_monitor",
      "directions": 4
    },
	{
      "name": "bishop_chest",
      "directions": 4
    },
	{
      "name": "bishop_l_arm",
      "directions": 4
    },
	{
      "name": "bishop_r_arm",
      "directions": 4
    },
	{
      "name": "bishop_l_leg",
      "directions": 4
    },
	{
      "name": "bishop_r_leg",
      "directions": 4
    },
	{
      "name": "bishop_l_hand",
      "directions": 4
    },
	{
      "name": "bishop_r_hand",
      "directions": 4
    },
	{
      "name": "bishop_l_foot",
      "directions": 4
    },
	{
      "name": "bishop_r_foot",
      "directions": 4
    },
	{
      "name": "xion_head",
      "directions": 4
    },
	{
      "name": "xion_head_monitor",
      "directions": 4
    },
	{
      "name": "xion_chest",
      "directions": 4
    },
	{
      "name": "xion_l_arm",
      "directions": 4
    },
	{
      "name": "xion_r_arm",
      "directions": 4
    },
	{
      "name": "xion_l_leg",
      "directions": 4
    },
	{
      "name": "xion_r_leg",
      "directions": 4
    },
	{
      "name": "xion_l_hand",
      "directions": 4
    },
	{
      "name": "xion_r_hand",
      "directions": 4
    },
	{
      "name": "xion_l_foot",
      "directions": 4
    },
	{
      "name": "xion_r_foot",
      "directions": 4
    }
  ]
}